tortreinador/__init__.py
tortreinador/train.py
tortreinador/models/MDN.py
tortreinador/models/__init__.py
tortreinador/utils/Recorder.py
tortreinador/utils/View.py
tortreinador/utils/WarmUpLR.py
tortreinador/utils/__init__.py
tortreinador/utils/cluster.py
tortreinador/utils/metrics.py
tortreinador/utils/plot.py
tortreinador/utils/preprocessing.py
tortreinador/utils/tools.py
tortreinador-0.2.3.dist-info/licenses/LICENSE
tortreinador-0.2.3.dist-info/METADATA
tortreinador-0.2.3.dist-info/WHEEL
tortreinador-0.2.3.dist-info/top_level.txt
tortreinador-0.2.3.dist-info/RECORD
